cpu_loader/__init__.py
cpu_loader/__main__.py
cpu_loader/cpu_loader.py
cpu_loader/cpu_loader_core.c
cpu_loader/cpu_loader_core.cpython-311-aarch64-linux-gnu.so
cpu_loader/example.py
cpu_loader/main.py
cpu_loader/mqtt_publisher.py
cpu_loader/static/favicon.svg
cpu_loader/templates/index.html
cpu_loader-0.8.1.dist-info/METADATA
cpu_loader-0.8.1.dist-info/WHEEL
cpu_loader-0.8.1.dist-info/entry_points.txt
cpu_loader-0.8.1.dist-info/top_level.txt
cpu_loader-0.8.1.dist-info/RECORD
cpu_loader-0.8.1.dist-info/licenses/LICENSE
