Metadata-Version: 2.4
Name: cpu-loader
Version: 0.8.1
Summary: A tool to generate CPU load on a system with runtime configuration through a WebUI and REST API
Author-email: the78mole <the78mole@users.noreply.github.com>
License: MIT
Project-URL: Homepage, https://github.com/the78mole/cpu-loader
Project-URL: Repository, https://github.com/the78mole/cpu-loader
Project-URL: Issues, https://github.com/the78mole/cpu-loader/issues
Project-URL: Changelog, https://github.com/the78mole/cpu-loader/releases
Keywords: cpu,load,testing,stress-test,performance,benchmark
Classifier: Development Status :: 4 - Beta
Classifier: Intended Audience :: Developers
Classifier: Intended Audience :: System Administrators
Classifier: Operating System :: POSIX :: Linux
Classifier: Operating System :: MacOS
Classifier: Programming Language :: Python :: 3
Classifier: Programming Language :: Python :: 3.9
Classifier: Programming Language :: Python :: 3.10
Classifier: Programming Language :: Python :: 3.11
Classifier: Programming Language :: Python :: 3.12
Classifier: Programming Language :: C
Classifier: Topic :: System :: Benchmark
Classifier: Topic :: System :: Monitoring
Requires-Python: >=3.9
License-File: LICENSE
Requires-Dist: fastapi==0.124.0
Requires-Dist: uvicorn[standard]==0.38.0
Requires-Dist: pydantic==2.12.5
Requires-Dist: requests==2.32.5
Requires-Dist: psutil>=5.9.0
Requires-Dist: websockets>=12.0
Requires-Dist: paho-mqtt>=2.1.0
Dynamic: license-file
